fipiran_nav/__init__.py
fipiran_nav/core.py
fipiran_nav/csv_export.py
fipiran_nav-1.0.8.dist-info/METADATA
fipiran_nav-1.0.8.dist-info/WHEEL
fipiran_nav-1.0.8.dist-info/top_level.txt
fipiran_nav-1.0.8.dist-info/RECORD
