Metadata-Version: 2.4
Name: fipiran_nav
Version: 1.0.8
Summary: Simple library to fetch Iranian fund data from fipiran.ir
Home-page: https://github.com/Kimiaslhd/fipiran_nav
Author: Kimia Salehy Delarestaghy
Author-email: kimiaslhd@gmail.com
Requires-Python: >=3.7
Requires-Dist: requests>=2.25.0
Dynamic: author
Dynamic: author-email
Dynamic: home-page
Dynamic: requires-dist
Dynamic: requires-python
Dynamic: summary
